setup.py
rwci/__init__.py
rwci/client.py
rwci/errors.py
rwci/message.py
rwci/user.py
rwci.py.egg-info/PKG-INFO
rwci.py.egg-info/SOURCES.txt
rwci.py.egg-info/dependency_links.txt
rwci.py.egg-info/requires.txt
rwci.py.egg-info/top_level.txt